rust_neotools-0.0.6.dist-info/METADATA
rust_neotools-0.0.6.dist-info/WHEEL
rust_neotools-0.0.6.dist-info/licenses/LICENSE
rust_neotools/__init__.py
rust_neotools/py.typed
rust_neotools/rust_neotools.cpython-311-aarch64-linux-gnu.so
rust_neotools/rust_neotools.pyi
rust_neotools-0.0.6.dist-info/RECORD
