Metadata-Version: 2.4
Name: rust_neotools
Version: 0.0.6
Classifier: Programming Language :: Rust
Classifier: Programming Language :: Python :: 3.11
Classifier: Programming Language :: Python :: 3.12
Classifier: Programming Language :: Python :: 3.13
Classifier: Programming Language :: Python :: 3.14
Classifier: Typing :: Typed
License-File: LICENSE
Summary: A Rust implementation of PHP 5's RNG to run some Neopets math, with python bindings.
Author: diceroll123
Requires-Python: >=3.11
Project-URL: Repository, https://github.com/diceroll123/rust_neotools
